displayer/__init__.py
displayer/displayer.py
displayer/dummy.gif
displayer/jquery-3.3.1.min.js
displayer/lazysizes.min.js
displayer/okzoom.min.js
displayer-0.4.2.dist-info/LICENSE
displayer-0.4.2.dist-info/METADATA
displayer-0.4.2.dist-info/WHEEL
displayer-0.4.2.dist-info/entry_points.txt
displayer-0.4.2.dist-info/top_level.txt
displayer-0.4.2.dist-info/RECORD
